LimeRTD/__init__.py
LimeRTD/read_rtd.py
LimeRTD-1.0.2.dist-info/METADATA
LimeRTD-1.0.2.dist-info/WHEEL
LimeRTD-1.0.2.dist-info/top_level.txt
LimeRTD-1.0.2.dist-info/RECORD
