Metadata-Version: 2.1
Name: LimeRTD
Version: 1.0.2
Summary: Decode the RTD file generated by KingPower Software.
Author-email: Lime AI Celltesting <celltesting@lime.ai>
Project-URL: Homepage, https://github.com/limeaicell/LimeRTD
Project-URL: Bug Tracker, https://github.com/limeaicell/LimeRTD/issues
Classifier: Programming Language :: Python :: 3
Requires-Python: >=3.9
Requires-Dist: pandas
Requires-Dist: numpy
